MANIFEST.in
README.rst
VERSION
requirements.txt
setup.py
waf_brain/__init__.py
waf_brain/__main__.py
waf_brain/data.py
waf_brain/exceptions.py
waf_brain/helpers.py
waf_brain/inferring.py
waf_brain.egg-info/PKG-INFO
waf_brain.egg-info/SOURCES.txt
waf_brain.egg-info/dependency_links.txt
waf_brain.egg-info/entry_points.txt
waf_brain.egg-info/requires.txt
waf_brain.egg-info/top_level.txt
waf_brain/models/model_feat-11_botneck-101.h5
waf_brain/models/model_feat-3_botneck-20.h5
waf_brain/models/model_feat-3_botneck-40.h5
waf_brain/models/model_feat-5_botneck-101.h5
waf_brain/models/model_feat-7_botneck-101.h5
waf_brain/service/__init__.py
waf_brain/service/end_points_waf.py
waf_brain/service/end_points_waf_simulator.py
waf_brain/service/make_web_app.py