Metadata-Version: 1.1
Name: waf-brain
Version: 1.0.0
Summary: WAF-brain: the clever and efficient Firewall for the Web
Home-page: https://github.com/bbva/waf-brain
Author: UNKNOWN
Author-email: UNKNOWN
License: Apache2
Platform: UNKNOWN
Classifier: Environment :: Console
Classifier: Intended Audience :: System Administrators
Classifier: Intended Audience :: Other Audience
Classifier: License :: OSI Approved :: BSD License
Classifier: Operating System :: MacOS
Classifier: Operating System :: Microsoft :: Windows
Classifier: Operating System :: POSIX
Classifier: Programming Language :: Python :: 3.6
